iflow_mcp_mcp_tool-1.0.0.dist-info/licenses/LICENSE
weather_server/__init__.py
weather_server/models.py
weather_server/server.py
weather_server/utils.py
iflow_mcp_mcp_tool-1.0.0.dist-info/METADATA
iflow_mcp_mcp_tool-1.0.0.dist-info/WHEEL
iflow_mcp_mcp_tool-1.0.0.dist-info/entry_points.txt
iflow_mcp_mcp_tool-1.0.0.dist-info/top_level.txt
iflow_mcp_mcp_tool-1.0.0.dist-info/RECORD
