Metadata-Version: 2.4
Name: iflow-mcp_mcp-tool
Version: 1.0.0
Summary: 一个基于 FastMCP 的天气查询服务
Author: Mr.Car
Author-email: "Mr.Car" <534192336car@gmail.com>
License: MIT
Project-URL: Source, https://github.com/MrCare/mcp_tool
Project-URL: Bug Reports, https://github.com/MrCare/mcp_tool/issues
Keywords: weather,mcp,fastmcp,api
Classifier: Programming Language :: Python :: 3.12
Classifier: Operating System :: OS Independent
Classifier: Development Status :: 4 - Beta
Classifier: Intended Audience :: Developers
Classifier: Topic :: Internet :: WWW/HTTP
Classifier: Topic :: Scientific/Engineering :: Atmospheric Science
Classifier: License :: OSI Approved :: MIT License
Requires-Python: >=3.12.0
License-File: LICENSE
Requires-Dist: fastmcp<0.5.0,>=0.4.1
Requires-Dist: httpx<0.29.0,>=0.28.1
Requires-Dist: python-dotenv<2.0.0,>=1.0.1
Requires-Dist: pinyin<0.5.0,>=0.4.0
Dynamic: author
Dynamic: license-file
Dynamic: requires-python
